atlassian_page_client/__init__.py
atlassian_page_client/attachment_client.py
atlassian_page_client/blog_client.py
atlassian_page_client/client_factory.py
atlassian_page_client/page.py
atlassian_page_client/page_client.py
atlassian_page_client/page_content.py
atlassian_page_client-0.2.2.dist-info/licenses/LICENSE
atlassian_page_client-0.2.2.dist-info/METADATA
atlassian_page_client-0.2.2.dist-info/WHEEL
atlassian_page_client-0.2.2.dist-info/top_level.txt
atlassian_page_client-0.2.2.dist-info/RECORD
