Metadata-Version: 2.4
Name: atlassian-page-client
Version: 0.2.2
Summary: A Python client library for interacting with Atlassian Confluence pages
Author-email: Yannick Zimmermann <yannick.zimmermann@proton.me>
Project-URL: Homepage, https://github.com/zimmer-yan/py-atlassian-page-client
Project-URL: Bug Reports, https://github.com/zimmer-yan/py-atlassian-page-client/issues
Project-URL: Source, https://github.com/zimmer-yan/py-atlassian-page-client
Keywords: atlassian,confluence,wiki,api,client
Classifier: Development Status :: 4 - Beta
Classifier: Intended Audience :: Developers
Classifier: License :: OSI Approved :: MIT License
Classifier: Operating System :: OS Independent
Classifier: Programming Language :: Python :: 3
Classifier: Programming Language :: Python :: 3.8
Classifier: Programming Language :: Python :: 3.9
Classifier: Programming Language :: Python :: 3.10
Classifier: Programming Language :: Python :: 3.11
Classifier: Programming Language :: Python :: 3.12
Classifier: Topic :: Internet :: WWW/HTTP :: Dynamic Content
Classifier: Topic :: Software Development :: Libraries :: Python Modules
Requires-Python: >=3.8
License-File: LICENSE
Requires-Dist: requests>=2.25.0
Requires-Dist: beautifulsoup4>=4.9.0
Provides-Extra: dev
Requires-Dist: pytest>=6.0; extra == "dev"
Requires-Dist: pytest-cov>=2.0; extra == "dev"
Requires-Dist: pytest-mock>=3.6.1; extra == "dev"
Requires-Dist: black>=21.0; extra == "dev"
Requires-Dist: flake8>=3.8; extra == "dev"
Requires-Dist: mypy>=0.812; extra == "dev"
Dynamic: license-file
